nougat_wrapper/__init__.py
nougat_wrapper/__main__.py
nougat_wrapper/cli.py
nougat_wrapper/core.py
nougat_wrapper/py.typed
nougat_ocr_cli-0.1.3.dist-info/METADATA
nougat_ocr_cli-0.1.3.dist-info/WHEEL
nougat_ocr_cli-0.1.3.dist-info/entry_points.txt
nougat_ocr_cli-0.1.3.dist-info/licenses/LICENSE
nougat_ocr_cli-0.1.3.dist-info/RECORD
