Metadata-Version: 2.4
Name: nougat-ocr-cli
Version: 0.1.3
Summary: Simple CLI wrapper for Nougat OCR with GPU acceleration support
Project-URL: Homepage, https://github.com/rubenffuertes/nougat-ocr-cli
Project-URL: Repository, https://github.com/rubenffuertes/nougat-ocr-cli
Project-URL: Issues, https://github.com/rubenffuertes/nougat-ocr-cli/issues
Author-email: Ruben Fernandez-Fuertes <fernandezfuertesruben@gmail.com>
License: MIT
License-File: LICENSE
Keywords: cli,document,extraction,gpu,nougat,ocr,pdf
Classifier: Development Status :: 4 - Beta
Classifier: Environment :: Console
Classifier: Intended Audience :: Developers
Classifier: Intended Audience :: Science/Research
Classifier: License :: OSI Approved :: MIT License
Classifier: Operating System :: OS Independent
Classifier: Programming Language :: Python :: 3
Classifier: Programming Language :: Python :: 3.11
Classifier: Topic :: Scientific/Engineering :: Artificial Intelligence
Classifier: Topic :: Text Processing :: General
Classifier: Topic :: Utilities
Requires-Python: <3.13,>=3.11
Requires-Dist: albumentations==1.3.1
Requires-Dist: nougat-ocr>=0.1.17
Requires-Dist: pypdfium2<5.0.0,>=4.30.0
Requires-Dist: torch>=2.0.0
Requires-Dist: transformers<4.36.0,>=4.35.0
Provides-Extra: dev
Requires-Dist: pytest-cov>=4.0.0; extra == 'dev'
Requires-Dist: pytest>=7.0.0; extra == 'dev'
Requires-Dist: ruff>=0.1.0; extra == 'dev'
